tables_cleaner/__init__.py
tables_cleaner/app_settings.py
tables_cleaner/apps.py
tables_cleaner/clean.py
tables_cleaner/management/commands/clean_tables.py
tables_cleaner/management/commands/__pycache__/clean_tables.cpython-37.pyc
tables_cleaner/management/commands/__pycache__/clean_tables.cpython-38.pyc
tests/__init__.py
tests/models.py
tests/test_settings.py
tests/tests.py
django_tables_cleaner-0.1.4.dist-info/LICENSE
django_tables_cleaner-0.1.4.dist-info/METADATA
django_tables_cleaner-0.1.4.dist-info/WHEEL
django_tables_cleaner-0.1.4.dist-info/top_level.txt
django_tables_cleaner-0.1.4.dist-info/RECORD
