Metadata-Version: 2.1
Name: django-tables-cleaner
Version: 0.1.4
Summary: A Django app used to remove oldest records from specific db tables.
Home-page: https://github.com/morlandi/django-tables-cleaner
Author: Mario Orlandi
Author-email: morlandi@brainstorm.it
License: MIT
Platform: UNKNOWN
Classifier: Framework :: Django
Classifier: Development Status :: 5 - Production/Stable
Classifier: Intended Audience :: Developers
Classifier: License :: OSI Approved :: MIT License
Classifier: Operating System :: OS Independent
Classifier: Programming Language :: Python
Classifier: Programming Language :: Python :: 3
Classifier: Framework :: Django
Classifier: Framework :: Django :: 2.2
Classifier: Framework :: Django :: 3.0
